<?xml version="1.0" encoding="utf-8" ?><dwsync><file name="_animation.scss" server="chswebdesign.com" local="3557407164" remote="3527046000" Dst="-1" /><file name="_appearance.scss" server="chswebdesign.com" local="3557407164" remote="3527046000" Dst="-1" /><file name="_backface-visibility.scss" server="chswebdesign.com" local="3557407164" remote="3527046000" Dst="-1" /><file name="_background-image.scss" server="chswebdesign.com" local="3557407164" remote="3527046000" Dst="-1" /><file name="_background.scss" server="chswebdesign.com" local="3557407164" remote="3527046000" Dst="-1" /><file name="_border-image.scss" server="chswebdesign.com" local="3557407164" remote="3527046000" Dst="-1" /><file name="_border-radius.scss" server="chswebdesign.com" local="3557407164" remote="3527046000" Dst="-1" /><file name="_calc.scss" server="chswebdesign.com" local="3557407164" remote="3527046000" Dst="-1" /><file name="_box-sizing.scss" server="chswebdesign.com" local="3557407164" remote="3527046000" Dst="-1" /><file name="_columns.scss" server="chswebdesign.com" local="3557407164" remote="3527046000" Dst="-1" /><file name="_filter.scss" server="chswebdesign.com" local="3557407164" remote="3527046000" Dst="-1" /><file name="_flex-box.scss" server="chswebdesign.com" local="3557407164" remote="3527046000" Dst="-1" /><file name="_font-face.scss" server="chswebdesign.com" local="3557407165" remote="3527046000" Dst="-1" /><file name="_font-feature-settings.scss" server="chswebdesign.com" local="3557407165" remote="3527046000" Dst="-1" /><file name="_hidpi-media-query.scss" server="chswebdesign.com" local="3557407165" remote="3527046000" Dst="-1" /><file name="_hyphens.scss" server="chswebdesign.com" local="3557407165" remote="3527046000" Dst="-1" /><file name="_image-rendering.scss" server="chswebdesign.com" local="3557407165" remote="3527046000" Dst="-1" /><file name="_keyframes.scss" server="chswebdesign.com" local="3557407165" remote="3527046000" Dst="-1" /><file name="_placeholder.scss" server="chswebdesign.com" local="3557407165" remote="3527046000" Dst="-1" /><file name="_linear-gradient.scss" server="chswebdesign.com" local="3557407165" remote="3527046000" Dst="-1" /><file name="_perspective.scss" server="chswebdesign.com" local="3557407165" remote="3527046000" Dst="-1" /><file name="_transform.scss" server="chswebdesign.com" local="3557407166" remote="3527046000" Dst="-1" /><file name="_transition.scss" server="chswebdesign.com" local="3557407166" remote="3527046000" Dst="-1" /><file name="_radial-gradient.scss" server="chswebdesign.com" local="3557407166" remote="3527046000" Dst="-1" /><file name="_user-select.scss" server="chswebdesign.com" local="3557407166" remote="3527046000" Dst="-1" /></dwsync>